Workbook

Sheet Consolidated
A1: Gracie's Hair Care
A2: Potential Profits
A4: Brand | B4: Units on Hand | C4: Store Discount | D4: Average Cost | E4: Total Cost | F4: Average Unit Price | G4: Total Value | H4: Potential Profit
A5: A&G | B5: =SUM(Miami:Jacksonville!B5) -> 371 | C5: =AVERAGE(Miami:Jacksonville!C5) -> 40 | D5: 98.75 | E5: =B5*D5 -> 36636.25 | F5: =ROUND(D5/(1-0.32),2)-C5 -> 105.22 | G5: =B5*F5 -> 39036.62 | H5: =G5-E5 -> 2400.37
A6: Kenra | B6: =SUM(Miami:Jacksonville!B6) -> 355 | C6: =AVERAGE(Miami:Jacksonville!C6) -> 10 | D6: 127.45 | E6: =B6*D6 -> 45244.75 | F6: =ROUND(D6/(1-0.32),2)-C6 -> 177.43 | G6: =B6*F6 -> 62987.65 | H6: =G6-E6 -> 17742.9
A7: Aquage | B7: =SUM(Miami:Jacksonville!B7) -> 633 | C7: =AVERAGE(Miami:Jacksonville!C7) -> 26.666667 | D7: 118.75 | E7: =B7*D7 -> 75168.75 | F7: =ROUND(D7/(1-0.32),2)-C7 -> 147.96333 | G7: =B7*F7 -> 93660.79 | H7: =G7-E7 -> 18492.04
A8: Matrix | B8: =SUM(Miami:Jacksonville!B8) -> 485 | C8: =AVERAGE(Miami:Jacksonville!C8) -> 15 | D8: 101.48 | E8: =B8*D8 -> 49217.8 | F8: =ROUND(D8/(1-0.32),2)-C8 -> 134.24 | G8: =B8*F8 -> 65106.4 | H8: =G8-E8 -> 15888.6
A9: Paul Mitchell | B9: =SUM(Miami:Jacksonville!B9) -> 555 | C9: =AVERAGE(Miami:Jacksonville!C9) -> 28.333333 | D9: 135.27 | E9: =B9*D9 -> 75074.85 | F9: =ROUND(D9/(1-0.32),2)-C9 -> 170.59667 | G9: =B9*F9 -> 94681.15 | H9: =G9-E9 -> 19606.3
A10: Redken | B10: =SUM(Miami:Jacksonville!B10) -> 679 | C10: =AVERAGE(Miami:Jacksonville!C10) -> 30 | D10: 165.8 | E10: =B10*D10 -> 112578.2 | F10: =ROUND(D10/(1-0.32),2)-C10 -> 213.82 | G10: =B10*F10 -> 145183.78 | H10: =G10-E10 -> 32605.58
A11: Biometrix | B11: =SUM(Miami:Jacksonville!B11) -> 685 | C11: =AVERAGE(Miami:Jacksonville!C11) -> 55 | D11: 110.25 | E11: =B11*D11 -> 75521.25 | F11: =ROUND(D11/(1-0.32),2)-C11 -> 107.13 | G11: =B11*F11 -> 73384.05 | H11: =G11-E11 -> -2137.2
B12: =SUM(B5:B11) -> 3763 | E12: =SUM(E5:E11) -> 469441.85 | G12: =SUM(G5:G11) -> 574040.44 | H12: =SUM(H5:H11) -> 104598.59
A13: Rounded Total | B13: =ROUND(B12,-2) -> 3800
A16: Gracie's Hair Care
A17: 245 Sunny Lane
A18: Tampa, Florida 33601

Sheet Printout2

Sheet Miami
A1: Gracie's Hair Care
A2: Miami Profits
A4: Brand | B4: Units on Hand | C4: Store Discount | D4: Average Cost | E4: Total Cost | F4: Average Unit Price | G4: Total Value | H4: Potential Profit
A5: A&G | B5: 100 | C5: 35 | D5: 98.75 | E5: =B5*D5 -> 9875 | F5: =ROUND(D5/(1-0.32),2)-C5 -> 110.22 | G5: =B5*F5 -> 11022 | H5: =G5-E5 -> 1147
A6: Kenra | B6: 119 | C6: 0 | D6: 127.45 | E6: =B6*D6 -> 15166.55 | F6: =ROUND(D6/(1-0.32),2)-C6 -> 187.43 | G6: =B6*F6 -> 22304.17 | H6: =G6-E6 -> 7137.62
A7: Aquage | B7: 135 | C7: 15 | D7: 118.75 | E7: =B7*D7 -> 16031.25 | F7: =ROUND(D7/(1-0.32),2)-C7 -> 159.63 | G7: =B7*F7 -> 21550.05 | H7: =G7-E7 -> 5518.8
A8: Matrix | B8: 180 | C8: 35 | D8: 101.48 | E8: =B8*D8 -> 18266.4 | F8: =ROUND(D8/(1-0.32),2)-C8 -> 114.24 | G8: =B8*F8 -> 20563.2 | H8: =G8-E8 -> 2296.8
A9: Paul Mitchell | B9: 255 | C9: 60 | D9: 135.27 | E9: =B9*D9 -> 34493.85 | F9: =ROUND(D9/(1-0.32),2)-C9 -> 138.93 | G9: =B9*F9 -> 35427.15 | H9: =G9-E9 -> 933.3
A10: Redken | B10: 179 | C10: 10 | D10: 165.8 | E10: =B10*D10 -> 29678.2 | F10: =ROUND(D10/(1-0.32),2)-C10 -> 233.82 | G10: =B10*F10 -> 41853.78 | H10: =G10-E10 -> 12175.58
A11: Biometrix | B11: 201 | C11: 50 | D11: 110.25 | E11: =B11*D11 -> 22160.25 | F11: =ROUND(D11/(1-0.32),2)-C11 -> 112.13 | G11: =B11*F11 -> 22538.13 | H11: =G11-E11 -> 377.88
B12: =SUM(B5:B11) -> 1169 | E12: =SUM(E5:E11) -> 145671.5 | G12: =SUM(G5:G11) -> 175258.48 | H12: =SUM(H5:H11) -> 29586.98
A16: Gracie's Hair Care
A17: 245 Sunny Lane
A18: Tampa, Florida 33601

Sheet Orlando
A1: Gracie's Hair Care
A2: Orlando Profits
A4: Brand | B4: Units on Hand | C4: Store Discount | D4: Average Cost | E4: Total Cost | F4: Average Unit Price | G4: Total Value | H4: Potential Profit
A5: A&G | B5: 75 | C5: 35 | D5: 98.75 | E5: =B5*D5 -> 7406.25 | F5: =ROUND(D5/(1-0.32),2)-C5 -> 110.22 | G5: =B5*F5 -> 8266.5 | H5: =G5-E5 -> 860.25
A6: Kenra | B6: 135 | C6: 15 | D6: 127.45 | E6: =B6*D6 -> 17205.75 | F6: =ROUND(D6/(1-0.32),2)-C6 -> 172.43 | G6: =B6*F6 -> 23278.05 | H6: =G6-E6 -> 6072.3
A7: Aquage | B7: 200 | C7: 30 | D7: 118.75 | E7: =B7*D7 -> 23750 | F7: =ROUND(D7/(1-0.32),2)-C7 -> 144.63 | G7: =B7*F7 -> 28926 | H7: =G7-E7 -> 5176
A8: Matrix | B8: 146 | C8: 10 | D8: 101.48 | E8: =B8*D8 -> 14816.08 | F8: =ROUND(D8/(1-0.32),2)-C8 -> 139.24 | G8: =B8*F8 -> 20329.04 | H8: =G8-E8 -> 5512.96
A9: Paul Mitchell | B9: 90 | C9: 0 | D9: 135.27 | E9: =B9*D9 -> 12174.3 | F9: =ROUND(D9/(1-0.32),2)-C9 -> 198.93 | G9: =B9*F9 -> 17903.7 | H9: =G9-E9 -> 5729.4
A10: Redken | B10: 175 | C10: 25 | D10: 165.8 | E10: =B10*D10 -> 29015 | F10: =ROUND(D10/(1-0.32),2)-C10 -> 218.82 | G10: =B10*F10 -> 38293.5 | H10: =G10-E10 -> 9278.5
A11: Biometrix | B11: 225 | C11: 60 | D11: 110.25 | E11: =B11*D11 -> 24806.25 | F11: =ROUND(D11/(1-0.32),2)-C11 -> 102.13 | G11: =B11*F11 -> 22979.25 | H11: =G11-E11 -> -1827
B12: =SUM(B5:B11) -> 1046 | E12: =SUM(E5:E11) -> 129173.63 | G12: =SUM(G5:G11) -> 159976.04 | H12: =SUM(H5:H11) -> 30802.41
A16: Gracie's Hair Care
A17: 245 Sunny Lane
A18: Tampa, Florida 33601

Sheet Jacksonville
A1: Gracie's Hair Care
A2: Jacksonville Profits
A4: Brand | B4: Units on Hand | C4: Store Discount | D4: Average Cost | E4: Total Cost | F4: Average Unit Price | G4: Total Value | H4: Potential Profit
A5: A&G | B5: 196 | C5: 50 | D5: 98.75 | E5: =B5*D5 -> 19355 | F5: =ROUND(D5/(1-0.32),2)-C5 -> 95.22 | G5: =B5*F5 -> 18663.12 | H5: =G5-E5 -> -691.88
A6: Kenra | B6: 101 | C6: 15 | D6: 127.45 | E6: =B6*D6 -> 12872.45 | F6: =ROUND(D6/(1-0.32),2)-C6 -> 172.43 | G6: =B6*F6 -> 17415.43 | H6: =G6-E6 -> 4542.98
A7: Aquage | B7: 298 | C7: 35 | D7: 118.75 | E7: =B7*D7 -> 35387.5 | F7: =ROUND(D7/(1-0.32),2)-C7 -> 139.63 | G7: =B7*F7 -> 41609.74 | H7: =G7-E7 -> 6222.24
A8: Matrix | B8: 159 | C8: 0 | D8: 101.48 | E8: =B8*D8 -> 16135.32 | F8: =ROUND(D8/(1-0.32),2)-C8 -> 149.24 | G8: =B8*F8 -> 23729.16 | H8: =G8-E8 -> 7593.84
A9: Paul Mitchell | B9: 210 | C9: 25 | D9: 135.27 | E9: =B9*D9 -> 28406.7 | F9: =ROUND(D9/(1-0.32),2)-C9 -> 173.93 | G9: =B9*F9 -> 36525.3 | H9: =G9-E9 -> 8118.6
A10: Redken | B10: 325 | C10: 55 | D10: 165.8 | E10: =B10*D10 -> 53885 | F10: =ROUND(D10/(1-0.32),2)-C10 -> 188.82 | G10: =B10*F10 -> 61366.5 | H10: =G10-E10 -> 7481.5
A11: Biometrix | B11: 259 | C11: 55 | D11: 110.25 | E11: =B11*D11 -> 28554.75 | F11: =ROUND(D11/(1-0.32),2)-C11 -> 107.13 | G11: =B11*F11 -> 27746.67 | H11: =G11-E11 -> -808.08
B12: =SUM(B5:B11) -> 1548 | E12: =SUM(E5:E11) -> 194596.72 | G12: =SUM(G5:G11) -> 227055.92 | H12: =SUM(H5:H11) -> 32459.2
A16: Gracie's Hair Care
A17: 245 Sunny Lane
A18: Tampa, Florida 33601

Sheet Pivot_Chart
B1: Column Labels
B2: A&G | C2: Aquage | D2: Biometrix | E2: Kenra | F2: Matrix | G2: Paul Mitchell | H2: Redken | I2: Grand Total
A3: Sum of Potential | B3: 0.022948397 | C3: 0.17679053 | D3: -0.020432398 | E3: 0.16962848 | F3: 0.15190071 | G3: 0.18744325 | H3: 0.31172103 | I3: 1

Sheet Printout 7
