Workbook

Sheet Starting Point
A1: Customer | B1: January | C1: February | D1: March | E1: April | F1: May | G1: June
A3: Lakeside Trucking
A4: Gregor Machines
A5: Real Photography
A6: Genesis Production
A7: Landower Floral
A8: Jewell Enterprises

Sheet Period 1 Sales
A1: Customer | B1: January | C1: February | D1: March | E1: April | F1: May | G1: June | H1: 6 Month Sales | I1: Consultant Fee | J1: Federal Tax | K1: State Tax
I2: 0.1 | J2: 0.17 | K2: 0.11
A3: Lakeside Trucking | B3: 89450 | C3: 75340 | D3: 98224 | E3: 84231 | F3: 73455 | G3: 97549 | H3: =SUM(B3:G3) -> 518249 | I3: =H3*$I$2 -> 51824.9 | J3: =H3*$J$2 -> 88102.33 | K3: =H3*$K$2 -> 57007.39
A4: Gregor Machines | B4: 45210 | C4: 28340 | D4: 53400 | E4: 33199 | F4: 40390 | G4: 50122 | H4: =SUM(B4:G4) -> 250661 | I4: =H4*$I$2 -> 25066.1 | J4: =H4*$J$2 -> 42612.37 | K4: =H4*$K$2 -> 27572.71
A5: Real Photography | B5: 30219 | C5: 28590 | D5: 3464 | E5: 30891 | F5: 35489 | G5: 36400 | H5: =SUM(B5:G5) -> 165053 | I5: =H5*$I$2 -> 16505.3 | J5: =H5*$J$2 -> 28059.01 | K5: =H5*$K$2 -> 18155.83
A6: Genesis Production | B6: 65290 | C6: 51390 | D6: 79334 | E6: 72190 | F6: 75390 | G6: 83219 | H6: =SUM(B6:G6) -> 426813 | I6: =H6*$I$2 -> 42681.3 | J6: =H6*$J$2 -> 72558.21 | K6: =H6*$K$2 -> 46949.43
A7: Landower Floral | B7: 12168 | C7: 19355 | D7: 45209 | E7: 22188 | F7: 14228 | G7: 38766 | H7: =SUM(B7:G7) -> 151914 | I7: =H7*$I$2 -> 15191.4 | J7: =H7*$J$2 -> 25825.38 | K7: =H7*$K$2 -> 16710.54
A8: Jewell Enterprises | B8: 44329 | C8: 21809 | D8: 33490 | E8: 19765 | F8: 50801 | G8: 32188 | H8: =SUM(B8:G8) -> 202382 | I8: =H8*$I$2 -> 20238.2 | J8: =H8*$J$2 -> 34404.94 | K8: =H8*$K$2 -> 22262.02
A11: Blue Scape Consulting
A12: 11032 Robinson Drive
A13: Nashville, TN 37011
A14: 1-800-651-9923

Sheet Period 1 Sales - Formulas
A1: Customer | B1: January | C1: February | D1: March | E1: April | F1: May | G1: June | H1: 6 Month Sales | I1: Consultant Fee | J1: Federal Tax | K1: State Tax
I2: 0.1 | J2: 0.17 | K2: 0.11
A3: Lakeside Trucking | B3: 89450 | C3: 75340 | D3: 98224 | E3: 84231 | F3: 73455 | G3: 97549 | H3: =SUM(B3:G3) -> 518249 | I3: =H3*$I$2 -> 51824.9 | J3: =H3*$J$2 -> 88102.33 | K3: =H3*$K$2 -> 57007.39
A4: Gregor Machines | B4: 45210 | C4: 28340 | D4: 53400 | E4: 33199 | F4: 40390 | G4: 50122 | H4: =SUM(B4:G4) -> 250661 | I4: =H4*$I$2 -> 25066.1 | J4: =H4*$J$2 -> 42612.37 | K4: =H4*$K$2 -> 27572.71
A5: Real Photography | B5: 30219 | C5: 28590 | D5: 3464 | E5: 30891 | F5: 35489 | G5: 36400 | H5: =SUM(B5:G5) -> 165053 | I5: =H5*$I$2 -> 16505.3 | J5: =H5*$J$2 -> 28059.01 | K5: =H5*$K$2 -> 18155.83
A6: Genesis Production | B6: 65290 | C6: 51390 | D6: 79334 | E6: 72190 | F6: 75390 | G6: 83219 | H6: =SUM(B6:G6) -> 426813 | I6: =H6*$I$2 -> 42681.3 | J6: =H6*$J$2 -> 72558.21 | K6: =H6*$K$2 -> 46949.43
A7: Landower Floral | B7: 12168 | C7: 19355 | D7: 45209 | E7: 22188 | F7: 14228 | G7: 38766 | H7: =SUM(B7:G7) -> 151914 | I7: =H7*$I$2 -> 15191.4 | J7: =H7*$J$2 -> 25825.38 | K7: =H7*$K$2 -> 16710.54
A8: Jewell Enterprises | B8: 44329 | C8: 21809 | D8: 33490 | E8: 19765 | F8: 50801 | G8: 32188 | H8: =SUM(B8:G8) -> 202382 | I8: =H8*$I$2 -> 20238.2 | J8: =H8*$J$2 -> 34404.94 | K8: =H8*$K$2 -> 22262.02
A11: Blue Scape Consulting
A12: 11032 Robinson Drive
A13: Nashville, TN 37011
A14: 1-800-651-9923

Sheet Period 2 Sales
A1: Customer | B1: January | C1: February | D1: March | E1: April | F1: May | G1: June | H1: 6 Month Sales | I1: Consultant Fee | J1: Federal Tax | K1: State Tax
I2: 0.1 | J2: 0.17 | K2: 0.11
A3: Lakeside Trucking | B3: 89450 | C3: 75340 | D3: 98224 | E3: 84231 | F3: 73455 | G3: 97549 | H3: =SUM(B3:G3) -> 518249 | I3: =H3*$I$2 -> 51824.9 | J3: =H3*$J$2 -> 88102.33 | K3: =H3*$K$2 -> 57007.39
A4: Gregor Machines | B4: 45210 | C4: 28340 | D4: 53400 | E4: 33199 | F4: 40390 | G4: 50122 | H4: =SUM(B4:G4) -> 250661 | I4: =H4*$I$2 -> 25066.1 | J4: =H4*$J$2 -> 42612.37 | K4: =H4*$K$2 -> 27572.71
A5: Real Photography | B5: 30219 | C5: 28590 | D5: 3464 | E5: 30891 | F5: 35489 | G5: 36400 | H5: =SUM(B5:G5) -> 165053 | I5: =H5*$I$2 -> 16505.3 | J5: =H5*$J$2 -> 28059.01 | K5: =H5*$K$2 -> 18155.83
A6: Genesis Production | B6: 65290 | C6: 51390 | D6: 79334 | E6: 72190 | F6: 75390 | G6: 83219 | H6: =SUM(B6:G6) -> 426813 | I6: =H6*$I$2 -> 42681.3 | J6: =H6*$J$2 -> 72558.21 | K6: =H6*$K$2 -> 46949.43
A7: Landower Floral | B7: 12168 | C7: 19355 | D7: 45209 | E7: 22188 | F7: 14228 | G7: 38766 | H7: =SUM(B7:G7) -> 151914 | I7: =H7*$I$2 -> 15191.4 | J7: =H7*$J$2 -> 25825.38 | K7: =H7*$K$2 -> 16710.54
A8: Jewell Enterprises | B8: 44329 | C8: 21809 | D8: 33490 | E8: 19765 | F8: 50801 | G8: 32188 | H8: =SUM(B8:G8) -> 202382 | I8: =H8*$I$2 -> 20238.2 | J8: =H8*$J$2 -> 34404.94 | K8: =H8*$K$2 -> 22262.02
A11: Blue Scape Consulting
A12: 11032 Robinson Drive
A13: Nashville, TN 37011
A14: 1-800-651-9923

Sheet Summary
A1: Customer | B1: Sales Yearly Total | C1: Consultant Fee Yearly Total | D1: Federal Tax Yearly Total | E1: State Tax Yearly Total | F1: Total Expenses | G1: Profit Yearly Total
A2: Lakeside Trucking | B2: =SUM('Period 1 Sales:Period 2 Sales'!H3) -> 1554747 | C2: =SUM('Period 1 Sales:Period 2 Sales'!I3) -> 155474.7 | D2: =SUM('Period 1 Sales:Period 2 Sales'!J3) -> 264306.99 | E2: =SUM('Period 1 Sales:Period 2 Sales'!K3) -> 171022.17 | F2: =SUM(C2:E2) -> 590803.86 | G2: =B2-F2 -> 963943.14
A3: Gregor Machines | B3: =SUM('Period 1 Sales:Period 2 Sales'!H4) -> 751983 | C3: =SUM('Period 1 Sales:Period 2 Sales'!I4) -> 75198.3 | D3: =SUM('Period 1 Sales:Period 2 Sales'!J4) -> 127837.11 | E3: =SUM('Period 1 Sales:Period 2 Sales'!K4) -> 82718.13 | F3: =SUM(C3:E3) -> 285753.54 | G3: =B3-F3 -> 466229.46
A4: Real Photography | B4: =SUM('Period 1 Sales:Period 2 Sales'!H5) -> 495159 | C4: =SUM('Period 1 Sales:Period 2 Sales'!I5) -> 49515.9 | D4: =SUM('Period 1 Sales:Period 2 Sales'!J5) -> 84177.03 | E4: =SUM('Period 1 Sales:Period 2 Sales'!K5) -> 54467.49 | F4: =SUM(C4:E4) -> 188160.42 | G4: =B4-F4 -> 306998.58
A5: Genesis Production | B5: =SUM('Period 1 Sales:Period 2 Sales'!H6) -> 1280439 | C5: =SUM('Period 1 Sales:Period 2 Sales'!I6) -> 128043.9 | D5: =SUM('Period 1 Sales:Period 2 Sales'!J6) -> 217674.63 | E5: =SUM('Period 1 Sales:Period 2 Sales'!K6) -> 140848.29 | F5: =SUM(C5:E5) -> 486566.82 | G5: =B5-F5 -> 793872.18
A6: Landower Floral | B6: =SUM('Period 1 Sales:Period 2 Sales'!H7) -> 455742 | C6: =SUM('Period 1 Sales:Period 2 Sales'!I7) -> 45574.2 | D6: =SUM('Period 1 Sales:Period 2 Sales'!J7) -> 77476.14 | E6: =SUM('Period 1 Sales:Period 2 Sales'!K7) -> 50131.62 | F6: =SUM(C6:E6) -> 173181.96 | G6: =B6-F6 -> 282560.04
A7: Jewell Enterprises | B7: =SUM('Period 1 Sales:Period 2 Sales'!H8) -> 607146 | C7: =SUM('Period 1 Sales:Period 2 Sales'!I8) -> 60714.6 | D7: =SUM('Period 1 Sales:Period 2 Sales'!J8) -> 103214.82 | E7: =SUM('Period 1 Sales:Period 2 Sales'!K8) -> 66786.06 | F7: =SUM(C7:E7) -> 230715.48 | G7: =B7-F7 -> 376430.52
A11: Blue Scape Consulting
A12: 11032 Robinson Drive
A13: Nashville, TN 37011
A14: 1-800-651-9923

Sheet Summary - Formulas
A1: Customer | B1: Sales Yearly Total | C1: Consultant Fee Yearly Total | D1: Federal Tax Yearly Total | E1: State Tax Yearly Total | F1: Total Expenses | G1: Profit Yearly Total
A2: Lakeside Trucking | B2: =SUM('Period 1 Sales:Period 2 Sales'!H3) -> 1554747 | C2: =SUM('Period 1 Sales:Period 2 Sales'!I3) -> 155474.7 | D2: =SUM('Period 1 Sales:Period 2 Sales'!J3) -> 264306.99 | E2: =SUM('Period 1 Sales:Period 2 Sales'!K3) -> 171022.17 | F2: =SUM(C2:E2) -> 590803.86 | G2: =B2-F2 -> 963943.14
A3: Gregor Machines | B3: =SUM('Period 1 Sales:Period 2 Sales'!H4) -> 751983 | C3: =SUM('Period 1 Sales:Period 2 Sales'!I4) -> 75198.3 | D3: =SUM('Period 1 Sales:Period 2 Sales'!J4) -> 127837.11 | E3: =SUM('Period 1 Sales:Period 2 Sales'!K4) -> 82718.13 | F3: =SUM(C3:E3) -> 285753.54 | G3: =B3-F3 -> 466229.46
A4: Real Photography | B4: =SUM('Period 1 Sales:Period 2 Sales'!H5) -> 495159 | C4: =SUM('Period 1 Sales:Period 2 Sales'!I5) -> 49515.9 | D4: =SUM('Period 1 Sales:Period 2 Sales'!J5) -> 84177.03 | E4: =SUM('Period 1 Sales:Period 2 Sales'!K5) -> 54467.49 | F4: =SUM(C4:E4) -> 188160.42 | G4: =B4-F4 -> 306998.58
A5: Genesis Production | B5: =SUM('Period 1 Sales:Period 2 Sales'!H6) -> 1280439 | C5: =SUM('Period 1 Sales:Period 2 Sales'!I6) -> 128043.9 | D5: =SUM('Period 1 Sales:Period 2 Sales'!J6) -> 217674.63 | E5: =SUM('Period 1 Sales:Period 2 Sales'!K6) -> 140848.29 | F5: =SUM(C5:E5) -> 486566.82 | G5: =B5-F5 -> 793872.18
A6: Landower Floral | B6: =SUM('Period 1 Sales:Period 2 Sales'!H7) -> 455742 | C6: =SUM('Period 1 Sales:Period 2 Sales'!I7) -> 45574.2 | D6: =SUM('Period 1 Sales:Period 2 Sales'!J7) -> 77476.14 | E6: =SUM('Period 1 Sales:Period 2 Sales'!K7) -> 50131.62 | F6: =SUM(C6:E6) -> 173181.96 | G6: =B6-F6 -> 282560.04
A7: Jewell Enterprises | B7: =SUM('Period 1 Sales:Period 2 Sales'!H8) -> 607146 | C7: =SUM('Period 1 Sales:Period 2 Sales'!I8) -> 60714.6 | D7: =SUM('Period 1 Sales:Period 2 Sales'!J8) -> 103214.82 | E7: =SUM('Period 1 Sales:Period 2 Sales'!K8) -> 66786.06 | F7: =SUM(C7:E7) -> 230715.48 | G7: =B7-F7 -> 376430.52
A11: Blue Scape Consulting
A12: 11032 Robinson Drive
A13: Nashville, TN 37011
A14: 1-800-651-9923

Sheet Pivot Information
B1: Customers
B2: Genesis Production | C2: Gregor Machines | D2: Jewell Enterprises | E2: Lakeside Trucking | F2: Landower Floral | G2: Real Photography | H2: Grand Total
A3: Sum of Profit Yearly Total | B3: 529248.12 | C3: 310819.64 | D3: 250953.68 | E3: 642628.76 | F3: 188373.36 | G3: 204665.72 | H3: 2126689.3

Sheet Macro
