Workbook
Name California: '4th Qtr Sales'!$F$5:$F$9
Name California_Beach_Escape: '4th Qtr Sales'!$F$5:$F$9
Name Hawaiian: '4th Qtr Sales'!$F$10:$F$15
Name NewYork: '4th Qtr Sales'!$F$16:$F$21
Name Orlando: '4th Qtr Sales'!$F$22:$F$30
Name Portland: '4th Qtr Sales'!$F$31:$F$35

Sheet 4th Qtr Sales
A1: Tour Sales
A2: 4th Quarter 2023
A4: Date | B4: Client Last Name | C4: Client First Name | D4: Payment Method | E4: Payment Amount | F4: Tour Name
A5: 45231 | B5: Catawnee | C5: Lakota | D5: Credit Card | E5: ='Tour Costs'!$B$3 -> 4875 | F5: California Beach Escape
A6: 45229 | B6: Jones | C6: Bryan | D6: Credit Card | E6: ='Tour Costs'!$B$3 -> 4875 | F6: California Beach Escape
A7: 45243 | B7: Rodriguez | C7: Miguel | D7: Credit Card | E7: ='Tour Costs'!$B$3 -> 4875 | F7: California Beach Escape
A8: 45291 | B8: Thompsen | C8: Malik | D8: Credit Card | E8: ='Tour Costs'!$B$3 -> 4875 | F8: California Beach Escape
A9: 45250 | B9: Wu | C9: Feng | D9: Credit Card | E9: ='Tour Costs'!$B$3 -> 4875 | F9: California Beach Escape
A10: 45287 | B10: Grady | C10: Elijah | D10: Personal Check | E10: ='Tour Costs'!$B$4 -> 6550 | F10: Hawaiian Islands Retreat
A11: 45261 | B11: Lopez | C11: Maria | D11: Credit Card | E11: ='Tour Costs'!$B$4 -> 6550 | F11: Hawaiian Islands Retreat
A12: 45275 | B12: Morgan | C12: Trent | D12: Credit Card | E12: ='Tour Costs'!$B$4 -> 6550 | F12: Hawaiian Islands Retreat
A13: 45245 | B13: Palmer | C13: Corbin | D13: Credit Card | E13: ='Tour Costs'!$B$4 -> 6550 | F13: Hawaiian Islands Retreat
A14: 45282 | B14: Williams | C14: Nevaeh | D14: Credit Card | E14: ='Tour Costs'!$B$4 -> 6550 | F14: Hawaiian Islands Retreat
A15: 45227 | B15: Zhang | C15: Kai | D15: Credit Card | E15: ='Tour Costs'!$B$4 -> 6550 | F15: Hawaiian Islands Retreat
A16: 45254 | B16: Aziz | C16: Robert | D16: Credit Card | E16: ='Tour Costs'!$B$5 -> 4495 | F16: New York City Lights
A17: 45218 | B17: Chote | C17: Jonathan | D17: Credit Card | E17: ='Tour Costs'!$B$5 -> 4495 | F17: New York City Lights
A18: 45281 | B18: Garcia | C18: Carlos | D18: Credit Card | E18: ='Tour Costs'!$B$5 -> 4495 | F18: New York City Lights
A19: 45270 | B19: Khan | C19: Hiram | D19: Credit Card | E19: ='Tour Costs'!$B$5 -> 4495 | F19: New York City Lights
A20: 45209 | B20: Morton | C20: Tiffany | D20: Credit Card | E20: ='Tour Costs'!$B$5 -> 4495 | F20: New York City Lights
A21: 45234 | B21: Wolf | C21: Sebastian | D21: Credit Card | E21: ='Tour Costs'!$B$5 -> 4495 | F21: New York City Lights
A22: 45267 | B22: Baker | C22: Jacqueline | D22: Credit Card | E22: ='Tour Costs'!$B$6 -> 3960 | F22: Orlando Theme Park Experience
A23: 45240 | B23: Davis | C23: James | D23: Credit Card | E23: ='Tour Costs'!$B$6 -> 3960 | F23: Orlando Theme Park Experience
A24: 45219 | B24: Markell | C24: Amber | D24: Cash | E24: ='Tour Costs'!$B$6 -> 3960 | F24: Orlando Theme Park Experience
A25: 45276 | B25: Nguyen | C25: Emilee | D25: Credit Card | E25: ='Tour Costs'!$B$6 -> 3960 | F25: Orlando Theme Park Experience
A26: 45220 | B26: Patel | C26: Inaya | D26: Credit Card | E26: ='Tour Costs'!$B$6 -> 3960 | F26: Orlando Theme Park Experience
A27: 45278 | B27: Rogers | C27: Sarah | D27: Cash | E27: ='Tour Costs'!$B$6 -> 3960 | F27: Orlando Theme Park Experience
A28: 45202 | B28: Smith | C28: Kischa | D28: Credit Card | E28: ='Tour Costs'!$B$6 -> 3960 | F28: Orlando Theme Park Experience
A29: 45248 | B29: Walters | C29: Jacob | D29: Credit Card | E29: ='Tour Costs'!$B$6 -> 3960 | F29: Orlando Theme Park Experience
A30: 45214 | B30: Wells | C30: Nancy | D30: Credit Card | E30: ='Tour Costs'!$B$6 -> 3960 | F30: Orlando Theme Park Experience
A31: 45204 | B31: Brady | C31: Monty | D31: Credit Card | E31: ='Tour Costs'!$B$7 -> 3125 | F31: Portland Kayak Adventure
A32: 45238 | B32: Hillis | C32: Alyssa | D32: Personal Check | E32: ='Tour Costs'!$B$7 -> 3125 | F32: Portland Kayak Adventure
A33: 45212 | B33: Johnson | C33: Wayne | D33: Credit Card | E33: ='Tour Costs'!$B$7 -> 3125 | F33: Portland Kayak Adventure
A34: 45237 | B34: Khatri | C34: Amar | D34: Credit Card | E34: ='Tour Costs'!$B$7 -> 3125 | F34: Portland Kayak Adventure
A35: 45273 | B35: Nader | C35: Rasheed | D35: Credit Card | E35: ='Tour Costs'!$B$7 -> 3125 | F35: Portland Kayak Adventure
A38: NUMBER OF TOURS SOLD
A39: California Beach Escape | D39: =COUNTA(California) -> 5
A40: Hawaiian Islands Retreat | D40: =COUNTA(Hawaiian) -> 6
A41: New York City Lights | D41: =COUNTA(NewYork) -> 6
A42: Orlando Theme Park Experience | D42: =COUNTA(Orlando) -> 9
A43: Portland Kayak Adventure | D43: =COUNTA(Portland) -> 5

Sheet Tour Costs
A1: Tour | B1: Cost
A3: California Beach Escape | B3: 4875
A4: Hawaiian Islands Retreat | B4: 6550
A5: New York City Lights | B5: 4495
A6: Orlando Theme Park Experience | B6: 3960
A7: Portland Kayak Adventure | B7: 3125
